meds/__init__.py
meds/_version.py
meds/py.typed
meds/schema.py
meds-0.4.1.dist-info/licenses/LICENSE
meds-0.4.1.dist-info/METADATA
meds-0.4.1.dist-info/WHEEL
meds-0.4.1.dist-info/top_level.txt
meds-0.4.1.dist-info/RECORD
