Metadata-Version: 2.4
Name: meds
Version: 0.4.1
Summary: A data standard for working with event stream data
Author-email: Matthew McDermott <mattmcdermott8@gmail.com>, Ethan Steinberg <ethanid@stanford.edu>, Tom Pollard <tpollard@mit.edu>, Robin van de Water <Robin.VandeWater@hpi.de>
License: Apache-2.0
Project-URL: Homepage, https://medical-event-data-standard.github.io/
Project-URL: Issues, https://github.com/Medical-Event-Data-Standard/meds/issues
Classifier: Programming Language :: Python :: 3
Classifier: License :: OSI Approved :: MIT License
Classifier: Operating System :: OS Independent
Requires-Python: >=3.10
License-File: LICENSE
Requires-Dist: pyarrow>=8
Requires-Dist: jsonschema>=4.0.0
Requires-Dist: typing_extensions>=4.0
Requires-Dist: flexible_schema~=0.1.0
Provides-Extra: dev
Requires-Dist: pre-commit<4; extra == "dev"
Requires-Dist: ruff; extra == "dev"
Provides-Extra: tests
Requires-Dist: pytest; extra == "tests"
Requires-Dist: pytest-cov[toml]; extra == "tests"
Dynamic: license-file
